README.md
setup.py
pyWireGuard_devel.egg-info/PKG-INFO
pyWireGuard_devel.egg-info/SOURCES.txt
pyWireGuard_devel.egg-info/dependency_links.txt
pyWireGuard_devel.egg-info/top_level.txt
pywireguard/__init__.py
pywireguard/constants.py
pywireguard/exceptions.py
pywireguard/interface.py
pywireguard/peer.py
pywireguard/wg_configparser.py
pywireguard/wireguard.py