Metadata-Version: 2.1
Name: pyWireGuard-devel
Version: 2019.12.0
Summary: Controller for WireGuard
Home-page: https://git.yurzs.dev/yurzs/pywireguard
Author: Yurzs (Yury)
Author-email: development+pyWireGuard-devel@yurzs.dev
License: MIT
Keywords: wireguard
Platform: UNKNOWN
Classifier: Development Status :: 3 - Alpha
Classifier: Intended Audience :: Developers
Classifier: Topic :: Software Development :: Build Tools
Classifier: License :: OSI Approved :: MIT License
Classifier: Programming Language :: Python :: 3
Classifier: Programming Language :: Python :: 3.8
Classifier: Programming Language :: Python :: 3.7
Classifier: Programming Language :: Python :: 3.6
